ashe/__init__.py
ashe/_date.py
ashe/_dict.py
ashe/_file.py
ashe/_list.py
ashe/_str.py
ashe/_sys.py
test/__init__.py
test/_date_test.py
test/_dict_test.py
test/_file_test.py
test/_list_test.py
test/_str_test.py
test/_sys_test.py
ashe-0.0.8.dist-info/LICENSE
ashe-0.0.8.dist-info/METADATA
ashe-0.0.8.dist-info/WHEEL
ashe-0.0.8.dist-info/top_level.txt
ashe-0.0.8.dist-info/zip-safe
ashe-0.0.8.dist-info/RECORD
