Metadata-Version: 2.1
Name: ashe
Version: 0.0.8
Summary: ashe is super extension of Python.
Home-page: https://github.com/Ailln/ashe
Author: Ailln
Author-email: kinggreenhall@gmail.com
License: MIT License
Classifier: Programming Language :: Python :: 3
Classifier: License :: OSI Approved :: MIT License
Classifier: Operating System :: OS Independent
Requires-Python: >=3.6
License-File: LICENSE
Requires-Dist: setuptools (>=40.6.3)
